build.sh
logo.svg
setup.py
Filterous.egg-info/PKG-INFO
Filterous.egg-info/SOURCES.txt
Filterous.egg-info/dependency_links.txt
Filterous.egg-info/entry_points.txt
Filterous.egg-info/requires.txt
Filterous.egg-info/top_level.txt
etc/bash_completion.d/filterous
filterous/__init__.py
filterous/filterous.py
tests/__init__.py
tests/tests.py