Metadata-Version: 1.0
Name: Filterous
Version: 0.8.2
Summary: Delicious Command Line Filter
Home-page: http://filterous.sourceforge.net/
Author: Victor Engmark
Author-email: victor.engmark@gmail.com
License: GPL v3 or newer
Download-URL: http://sourceforge.net/projects/filterous/files/
Keywords: Delicious filterous search bookmarks tags
Platform: POSIX
Platform: Windows
Classifier: Development Status :: 4 - Beta
Classifier: Environment :: Console
Classifier: Intended Audience :: End Users/Desktop
Classifier: License :: OSI Approved :: GNU General Public License (GPL)
Classifier: Natural Language :: English
Classifier: Operating System :: OS Independent
Classifier: Programming Language :: Python :: 2.6
Classifier: Topic :: Text Processing :: Filters
